etiennevar/__init__.py
etiennevar/cli.py
etiennevar/plotting.py
etiennevar-1.0.4.dist-info/METADATA
etiennevar-1.0.4.dist-info/WHEEL
etiennevar-1.0.4.dist-info/entry_points.txt
etiennevar-1.0.4.dist-info/top_level.txt
etiennevar-1.0.4.dist-info/RECORD
