Metadata-Version: 2.4
Name: etiennevar
Version: 1.0.4
Summary: Outil en ligne de commande pour résumer et visualiser les fichiers VCF
Author: Etienne Kabongo
Author-email: Etienne Kabongo <etienne.ntumba.kabongo@umontreal.ca>
License-Expression: MIT
Project-URL: Homepage, https://pypi.org/project/etiennevar
Project-URL: Repository, https://github.com/etiennekabongo/etiennevar
Keywords: vcf,bioinformatique,variant,cli,visualisation
Requires-Python: >=3.7
Requires-Dist: matplotlib
Requires-Dist: numpy
Requires-Dist: seaborn
Dynamic: author
Dynamic: requires-python
